ofg_auth_service_layer/__init__.py
ofg_auth_service_layer/auth_service.py
ofg_auth_service_layer/errors.py
ofg_auth_service_layer-0.1.0.dist-info/METADATA
ofg_auth_service_layer-0.1.0.dist-info/WHEEL
ofg_auth_service_layer-0.1.0.dist-info/top_level.txt
ofg_auth_service_layer-0.1.0.dist-info/RECORD
