Metadata-Version: 2.4
Name: ofg-auth-service-layer
Version: 0.1.0
Summary: Auth service layer (HubSpot token via AWS Secrets + API)
Author: OFG
Requires-Python: >=3.9
Requires-Dist: boto3>=1.28
Requires-Dist: httpx>=0.24
